[{"email":"example0@example.com","password":"password0"},{"email":"example1@example.com","password":"password1"},{"email":"example2@example.com","password":"password2"},{"email":"example3@example.com","password":"password3"},{"email":"example4@example.com","password":"password4"},{"email":"example5@example.com","password":"password5"},{"email":"example6@example.com","password":"password6"},{"email":"example7@example.com","password":"password7"},{"email":"example8@example.com","password":"password8"},{"email":"example9@example.com","password":"password9"},{"email":"example10@example.com","password":"password10"},{"email":"example11@example.com","password":"password11"},{"email":"example12@example.com","password":"password12"},{"email":"example13@example.com","password":"password13"},{"email":"example14@example.com","password":"password14"},{"email":"example15@example.com","password":"password15"},{"email":"example16@example.com","password":"password16"},{"email":"example17@example.com","password":"password17"},{"email":"example18@example.com","password":"password18"},{"email":"example19@example.com","password":"password19"},{"email":"example20@example.com","password":"password20"},{"email":"example21@example.com","password":"password21"},{"email":"example22@example.com","password":"password22"},{"email":"example23@example.com","password":"password23"},{"email":"example24@example.com","password":"password24"},{"email":"example25@example.com","password":"password25"},{"email":"example26@example.com","password":"password26"},{"email":"example27@example.com","password":"password27"},{"email":"example28@example.com","password":"password28"},{"email":"example29@example.com","password":"password29"},{"email":"example30@example.com","password":"password30"},{"email":"example31@example.com","password":"password31"},{"email":"example32@example.com","password":"password32"},{"email":"example33@example.com","password":"password33"},{"email":"example34@example.com","password":"password34"},{"email":"example35@example.com","password":"password35"},{"email":"example36@example.com","password":"password36"},{"email":"example37@example.com","password":"password37"},{"email":"example38@example.com","password":"password38"},{"email":"example39@example.com","password":"password39"},{"email":"example40@example.com","password":"password40"},{"email":"example41@example.com","password":"password41"},{"email":"example42@example.com","password":"password42"},{"email":"example43@example.com","password":"password43"},{"email":"example44@example.com","password":"password44"},{"email":"example45@example.com","password":"password45"},{"email":"example46@example.com","password":"password46"},{"email":"example47@example.com","password":"password47"},{"email":"example48@example.com","password":"password48"},{"email":"example49@example.com","password":"password49"},{"email":"example50@example.com","password":"password50"},{"email":"example51@example.com","password":"password51"},{"email":"example52@example.com","password":"password52"},{"email":"example53@example.com","password":"password53"},{"email":"example54@example.com","password":"password54"},{"email":"example55@example.com","password":"password55"},{"email":"example56@example.com","password":"password56"},{"email":"example57@example.com","password":"password57"},{"email":"example58@example.com","password":"password58"},{"email":"example59@example.com","password":"password59"},{"email":"example60@example.com","password":"password60"},{"email":"example61@example.com","password":"password61"},{"email":"example62@example.com","password":"password62"},{"email":"example63@example.com","password":"password63"},{"email":"example64@example.com","password":"password64"},{"email":"example65@example.com","password":"password65"},{"email":"example66@example.com","password":"password66"},{"email":"example67@example.com","password":"password67"},{"email":"example68@example.com","password":"password68"},{"email":"example69@example.com","password":"password69"},{"email":"example70@example.com","password":"password70"},{"email":"example71@example.com","password":"password71"},{"email":"example72@example.com","password":"password72"},{"email":"example73@example.com","password":"password73"},{"email":"example74@example.com","password":"password74"},{"email":"example75@example.com","password":"password75"},{"email":"example76@example.com","password":"password76"},{"email":"example77@example.com","password":"password77"},{"email":"example78@example.com","password":"password78"},{"email":"example79@example.com","password":"password79"},{"email":"example80@example.com","password":"password80"},{"email":"example81@example.com","password":"password81"},{"email":"example82@example.com","password":"password82"},{"email":"example83@example.com","password":"password83"},{"email":"example84@example.com","password":"password84"},{"email":"example85@example.com","password":"password85"},{"email":"example86@example.com","password":"password86"},{"email":"example87@example.com","password":"password87"},{"email":"example88@example.com","password":"password88"},{"email":"example89@example.com","password":"password89"},{"email":"example90@example.com","password":"password90"},{"email":"example91@example.com","password":"password91"},{"email":"example92@example.com","password":"password92"},{"email":"example93@example.com","password":"password93"},{"email":"example94@example.com","password":"password94"},{"email":"example95@example.com","password":"password95"},{"email":"example96@example.com","password":"password96"},{"email":"example97@example.com","password":"password97"},{"email":"example98@example.com","password":"password98"},{"email":"example99@example.com","password":"password99"},{"email":"example100@example.com","password":"password100"},{"email":"example101@example.com","password":"password101"},{"email":"example102@example.com","password":"password102"},{"email":"example103@example.com","password":"password103"},{"email":"example104@example.com","password":"password104"},{"email":"example105@example.com","password":"password105"},{"email":"example106@example.com","password":"password106"},{"email":"example107@example.com","password":"password107"},{"email":"example108@example.com","password":"password108"},{"email":"example109@example.com","password":"password109"},{"email":"example110@example.com","password":"password110"},{"email":"example111@example.com","password":"password111"},{"email":"example112@example.com","password":"password112"},{"email":"example113@example.com","password":"password113"},{"email":"example114@example.com","password":"password114"},{"email":"example115@example.com","password":"password115"},{"email":"example116@example.com","password":"password116"},{"email":"example117@example.com","password":"password117"},{"email":"example118@example.com","password":"password118"},{"email":"example119@example.com","password":"password119"},{"email":"example120@example.com","password":"password120"},{"email":"example121@example.com","password":"password121"},{"email":"example122@example.com","password":"password122"},{"email":"example123@example.com","password":"password123"},{"email":"example124@example.com","password":"password124"},{"email":"example125@example.com","password":"password125"},{"email":"example126@example.com","password":"password126"},{"email":"example127@example.com","password":"password127"},{"email":"example128@example.com","password":"password128"},{"email":"example129@example.com","password":"password129"},{"email":"example130@example.com","password":"password130"},{"email":"example131@example.com","password":"password131"},{"email":"example132@example.com","password":"password132"},{"email":"example133@example.com","password":"password133"},{"email":"example134@example.com","password":"password134"},{"email":"example135@example.com","password":"password135"},{"email":"example136@example.com","password":"password136"},{"email":"example137@example.com","password":"password137"},{"email":"example138@example.com","password":"password138"},{"email":"example139@example.com","password":"password139"},{"email":"example140@example.com","password":"password140"},{"email":"example141@example.com","password":"password141"},{"email":"example142@example.com","password":"password142"},{"email":"example143@example.com","password":"password143"},{"email":"example144@example.com","password":"password144"},{"email":"example145@example.com","password":"password145"},{"email":"example146@example.com","password":"password146"},{"email":"example147@example.com","password":"password147"},{"email":"example148@example.com","password":"password148"},{"email":"example149@example.com","password":"password149"},{"email":"example150@example.com","password":"password150"},{"email":"example151@example.com","password":"password151"},{"email":"example152@example.com","password":"password152"},{"email":"example153@example.com","password":"password153"},{"email":"example154@example.com","password":"password154"},{"email":"example155@example.com","password":"password155"},{"email":"example156@example.com","password":"password156"},{"email":"example157@example.com","password":"password157"},{"email":"example158@example.com","password":"password158"},{"email":"example159@example.com","password":"password159"},{"email":"example160@example.com","password":"password160"},{"email":"example161@example.com","password":"password161"},{"email":"example162@example.com","password":"password162"},{"email":"example163@example.com","password":"password163"},{"email":"example164@example.com","password":"password164"},{"email":"example165@example.com","password":"password165"},{"email":"example166@example.com","password":"password166"},{"email":"example167@example.com","password":"password167"},{"email":"example168@example.com","password":"password168"},{"email":"example169@example.com","password":"password169"},{"email":"example170@example.com","password":"password170"},{"email":"example171@example.com","password":"password171"},{"email":"example172@example.com","password":"password172"},{"email":"example173@example.com","password":"password173"},{"email":"example174@example.com","password":"password174"},{"email":"example175@example.com","password":"password175"},{"email":"example176@example.com","password":"password176"},{"email":"example177@example.com","password":"password177"},{"email":"example178@example.com","password":"password178"},{"email":"example179@example.com","password":"password179"},{"email":"example180@example.com","password":"password180"},{"email":"example181@example.com","password":"password181"},{"email":"example182@example.com","password":"password182"},{"email":"example183@example.com","password":"password183"},{"email":"example184@example.com","password":"password184"},{"email":"example185@example.com","password":"password185"},{"email":"example186@example.com","password":"password186"},{"email":"example187@example.com","password":"password187"},{"email":"example188@example.com","password":"password188"},{"email":"example189@example.com","password":"password189"},{"email":"example190@example.com","password":"password190"},{"email":"example191@example.com","password":"password191"},{"email":"example192@example.com","password":"password192"},{"email":"example193@example.com","password":"password193"},{"email":"example194@example.com","password":"password194"},{"email":"example195@example.com","password":"password195"},{"email":"example196@example.com","password":"password196"},{"email":"example197@example.com","password":"password197"},{"email":"example198@example.com","password":"password198"},{"email":"example199@example.com","password":"password199"},{"email":"example200@example.com","password":"password200"},{"email":"example201@example.com","password":"password201"},{"email":"example202@example.com","password":"password202"},{"email":"example203@example.com","password":"password203"},{"email":"example204@example.com","password":"password204"},{"email":"example205@example.com","password":"password205"},{"email":"example206@example.com","password":"password206"},{"email":"example207@example.com","password":"password207"},{"email":"example208@example.com","password":"password208"},{"email":"example209@example.com","password":"password209"},{"email":"example210@example.com","password":"password210"},{"email":"example211@example.com","password":"password211"},{"email":"example212@example.com","password":"password212"},{"email":"example213@example.com","password":"password213"},{"email":"example214@example.com","password":"password214"},{"email":"example215@example.com","password":"password215"},{"email":"example216@example.com","password":"password216"},{"email":"example217@example.com","password":"password217"},{"email":"example218@example.com","password":"password218"},{"email":"example219@example.com","password":"password219"},{"email":"example220@example.com","password":"password220"},{"email":"example221@example.com","password":"password221"},{"email":"example222@example.com","password":"password222"},{"email":"example223@example.com","password":"password223"},{"email":"example224@example.com","password":"password224"},{"email":"example225@example.com","password":"password225"},{"email":"example226@example.com","password":"password226"},{"email":"example227@example.com","password":"password227"},{"email":"example228@example.com","password":"password228"},{"email":"example229@example.com","password":"password229"},{"email":"example230@example.com","password":"password230"},{"email":"example231@example.com","password":"password231"},{"email":"example232@example.com","password":"password232"},{"email":"example233@example.com","password":"password233"},{"email":"example234@example.com","password":"password234"},{"email":"example235@example.com","password":"password235"},{"email":"example236@example.com","password":"password236"},{"email":"example237@example.com","password":"password237"},{"email":"example238@example.com","password":"password238"},{"email":"example239@example.com","password":"password239"},{"email":"example240@example.com","password":"password240"},{"email":"example241@example.com","password":"password241"},{"email":"example242@example.com","password":"password242"},{"email":"example243@example.com","password":"password243"},{"email":"example244@example.com","password":"password244"},{"email":"example245@example.com","password":"password245"},{"email":"example246@example.com","password":"password246"},{"email":"example247@example.com","password":"password247"},{"email":"example248@example.com","password":"password248"},{"email":"example249@example.com","password":"password249"},{"email":"example250@example.com","password":"password250"},{"email":"example251@example.com","password":"password251"},{"email":"example252@example.com","password":"password252"},{"email":"example253@example.com","password":"password253"},{"email":"example254@example.com","password":"password254"},{"email":"example255@example.com","password":"password255"},{"email":"example256@example.com","password":"password256"},{"email":"example257@example.com","password":"password257"},{"email":"example258@example.com","password":"password258"},{"email":"example259@example.com","password":"password259"},{"email":"example260@example.com","password":"password260"},{"email":"example261@example.com","password":"password261"},{"email":"example262@example.com","password":"password262"},{"email":"example263@example.com","password":"password263"},{"email":"example264@example.com","password":"password264"},{"email":"example265@example.com","password":"password265"},{"email":"example266@example.com","password":"password266"},{"email":"example267@example.com","password":"password267"},{"email":"example268@example.com","password":"password268"},{"email":"example269@example.com","password":"password269"},{"email":"example270@example.com","password":"password270"},{"email":"example271@example.com","password":"password271"},{"email":"example272@example.com","password":"password272"},{"email":"example273@example.com","password":"password273"},{"email":"example274@example.com","password":"password274"},{"email":"example275@example.com","password":"password275"},{"email":"example276@example.com","password":"password276"},{"email":"example277@example.com","password":"password277"},{"email":"example278@example.com","password":"password278"},{"email":"example279@example.com","password":"password279"},{"email":"example280@example.com","password":"password280"},{"email":"example281@example.com","password":"password281"},{"email":"example282@example.com","password":"password282"},{"email":"example283@example.com","password":"password283"},{"email":"example284@example.com","password":"password284"},{"email":"example285@example.com","password":"password285"},{"email":"example286@example.com","password":"password286"},{"email":"example287@example.com","password":"password287"},{"email":"example288@example.com","password":"password288"},{"email":"example289@example.com","password":"password289"},{"email":"example290@example.com","password":"password290"},{"email":"example291@example.com","password":"password291"},{"email":"example292@example.com","password":"password292"},{"email":"example293@example.com","password":"password293"},{"email":"example294@example.com","password":"password294"},{"email":"example295@example.com","password":"password295"},{"email":"example296@example.com","password":"password296"},{"email":"example297@example.com","password":"password297"},{"email":"example298@example.com","password":"password298"},{"email":"example299@example.com","password":"password299"},{"email":"example300@example.com","password":"password300"},{"email":"example301@example.com","password":"password301"},{"email":"example302@example.com","password":"password302"},{"email":"example303@example.com","password":"password303"},{"email":"example304@example.com","password":"password304"},{"email":"example305@example.com","password":"password305"},{"email":"example306@example.com","password":"password306"},{"email":"example307@example.com","password":"password307"},{"email":"example308@example.com","password":"password308"},{"email":"example309@example.com","password":"password309"},{"email":"example310@example.com","password":"password310"},{"email":"example311@example.com","password":"password311"},{"email":"example312@example.com","password":"password312"},{"email":"example313@example.com","password":"password313"},{"email":"example314@example.com","password":"password314"},{"email":"example315@example.com","password":"password315"},{"email":"example316@example.com","password":"password316"},{"email":"example317@example.com","password":"password317"},{"email":"example318@example.com","password":"password318"},{"email":"example319@example.com","password":"password319"},{"email":"example320@example.com","password":"password320"},{"email":"example321@example.com","password":"password321"},{"email":"example322@example.com","password":"password322"},{"email":"example323@example.com","password":"password323"},{"email":"example324@example.com","password":"password324"},{"email":"example325@example.com","password":"password325"},{"email":"example326@example.com","password":"password326"},{"email":"example327@example.com","password":"password327"},{"email":"example328@example.com","password":"password328"},{"email":"example329@example.com","password":"password329"},{"email":"example330@example.com","password":"password330"},{"email":"example331@example.com","password":"password331"},{"email":"example332@example.com","password":"password332"},{"email":"example333@example.com","password":"password333"},{"email":"example334@example.com","password":"password334"},{"email":"example335@example.com","password":"password335"},{"email":"example336@example.com","password":"password336"},{"email":"example337@example.com","password":"password337"},{"email":"example338@example.com","password":"password338"},{"email":"example339@example.com","password":"password339"},{"email":"example340@example.com","password":"password340"},{"email":"example341@example.com","password":"password341"},{"email":"example342@example.com","password":"password342"},{"email":"example343@example.com","password":"password343"},{"email":"example344@example.com","password":"password344"},{"email":"example345@example.com","password":"password345"},{"email":"example346@example.com","password":"password346"},{"email":"example347@example.com","password":"password347"},{"email":"example348@example.com","password":"password348"},{"email":"example349@example.com","password":"password349"},{"email":"example350@example.com","password":"password350"},{"email":"example351@example.com","password":"password351"},{"email":"example352@example.com","password":"password352"},{"email":"example353@example.com","password":"password353"},{"email":"example354@example.com","password":"password354"},{"email":"example355@example.com","password":"password355"},{"email":"example356@example.com","password":"password356"},{"email":"example357@example.com","password":"password357"},{"email":"example358@example.com","password":"password358"},{"email":"example359@example.com","password":"password359"},{"email":"example360@example.com","password":"password360"},{"email":"example361@example.com","password":"password361"},{"email":"example362@example.com","password":"password362"},{"email":"example363@example.com","password":"password363"},{"email":"example364@example.com","password":"password364"},{"email":"example365@example.com","password":"password365"},{"email":"example366@example.com","password":"password366"},{"email":"example367@example.com","password":"password367"},{"email":"example368@example.com","password":"password368"},{"email":"example369@example.com","password":"password369"},{"email":"example370@example.com","password":"password370"},{"email":"example371@example.com","password":"password371"},{"email":"example372@example.com","password":"password372"},{"email":"example373@example.com","password":"password373"},{"email":"example374@example.com","password":"password374"},{"email":"example375@example.com","password":"password375"},{"email":"example376@example.com","password":"password376"},{"email":"example377@example.com","password":"password377"},{"email":"example378@example.com","password":"password378"},{"email":"example379@example.com","password":"password379"},{"email":"example380@example.com","password":"password380"},{"email":"example381@example.com","password":"password381"},{"email":"example382@example.com","password":"password382"},{"email":"example383@example.com","password":"password383"},{"email":"example384@example.com","password":"password384"},{"email":"example385@example.com","password":"password385"},{"email":"example386@example.com","password":"password386"},{"email":"example387@example.com","password":"password387"},{"email":"example388@example.com","password":"password388"},{"email":"example389@example.com","password":"password389"},{"email":"example390@example.com","password":"password390"},{"email":"example391@example.com","password":"password391"},{"email":"example392@example.com","password":"password392"},{"email":"example393@example.com","password":"password393"},{"email":"example394@example.com","password":"password394"},{"email":"example395@example.com","password":"password395"},{"email":"example396@example.com","password":"password396"},{"email":"example397@example.com","password":"password397"},{"email":"example398@example.com","password":"password398"},{"email":"example399@example.com","password":"password399"},{"email":"example400@example.com","password":"password400"},{"email":"example401@example.com","password":"password401"},{"email":"example402@example.com","password":"password402"},{"email":"example403@example.com","password":"password403"},{"email":"example404@example.com","password":"password404"},{"email":"example405@example.com","password":"password405"},{"email":"example406@example.com","password":"password406"},{"email":"example407@example.com","password":"password407"},{"email":"example408@example.com","password":"password408"},{"email":"example409@example.com","password":"password409"},{"email":"example410@example.com","password":"password410"},{"email":"example411@example.com","password":"password411"},{"email":"example412@example.com","password":"password412"},{"email":"example413@example.com","password":"password413"},{"email":"example414@example.com","password":"password414"},{"email":"example415@example.com","password":"password415"},{"email":"example416@example.com","password":"password416"},{"email":"example417@example.com","password":"password417"},{"email":"example418@example.com","password":"password418"},{"email":"example419@example.com","password":"password419"},{"email":"example420@example.com","password":"password420"},{"email":"example421@example.com","password":"password421"},{"email":"example422@example.com","password":"password422"},{"email":"example423@example.com","password":"password423"},{"email":"example424@example.com","password":"password424"},{"email":"example425@example.com","password":"password425"},{"email":"example426@example.com","password":"password426"},{"email":"example427@example.com","password":"password427"},{"email":"example428@example.com","password":"password428"},{"email":"example429@example.com","password":"password429"},{"email":"example430@example.com","password":"password430"},{"email":"example431@example.com","password":"password431"},{"email":"example432@example.com","password":"password432"},{"email":"example433@example.com","password":"password433"},{"email":"example434@example.com","password":"password434"},{"email":"example435@example.com","password":"password435"},{"email":"example436@example.com","password":"password436"},{"email":"example437@example.com","password":"password437"},{"email":"example438@example.com","password":"password438"},{"email":"example439@example.com","password":"password439"},{"email":"example440@example.com","password":"password440"},{"email":"example441@example.com","password":"password441"},{"email":"example442@example.com","password":"password442"},{"email":"example443@example.com","password":"password443"},{"email":"example444@example.com","password":"password444"},{"email":"example445@example.com","password":"password445"},{"email":"example446@example.com","password":"password446"},{"email":"example447@example.com","password":"password447"},{"email":"example448@example.com","password":"password448"},{"email":"example449@example.com","password":"password449"},{"email":"example450@example.com","password":"password450"},{"email":"example451@example.com","password":"password451"},{"email":"example452@example.com","password":"password452"},{"email":"example453@example.com","password":"password453"},{"email":"example454@example.com","password":"password454"},{"email":"example455@example.com","password":"password455"},{"email":"example456@example.com","password":"password456"},{"email":"example457@example.com","password":"password457"},{"email":"example458@example.com","password":"password458"},{"email":"example459@example.com","password":"password459"},{"email":"example460@example.com","password":"password460"},{"email":"example461@example.com","password":"password461"},{"email":"example462@example.com","password":"password462"},{"email":"example463@example.com","password":"password463"},{"email":"example464@example.com","password":"password464"},{"email":"example465@example.com","password":"password465"},{"email":"example466@example.com","password":"password466"},{"email":"example467@example.com","password":"password467"},{"email":"example468@example.com","password":"password468"},{"email":"example469@example.com","password":"password469"},{"email":"example470@example.com","password":"password470"},{"email":"example471@example.com","password":"password471"},{"email":"example472@example.com","password":"password472"},{"email":"example473@example.com","password":"password473"},{"email":"example474@example.com","password":"password474"},{"email":"example475@example.com","password":"password475"},{"email":"example476@example.com","password":"password476"},{"email":"example477@example.com","password":"password477"},{"email":"example478@example.com","password":"password478"},{"email":"example479@example.com","password":"password479"},{"email":"example480@example.com","password":"password480"},{"email":"example481@example.com","password":"password481"},{"email":"example482@example.com","password":"password482"},{"email":"example483@example.com","password":"password483"},{"email":"example484@example.com","password":"password484"},{"email":"example485@example.com","password":"password485"},{"email":"example486@example.com","password":"password486"},{"email":"example487@example.com","password":"password487"},{"email":"example488@example.com","password":"password488"},{"email":"example489@example.com","password":"password489"},{"email":"example490@example.com","password":"password490"},{"email":"example491@example.com","password":"password491"},{"email":"example492@example.com","password":"password492"},{"email":"example493@example.com","password":"password493"},{"email":"example494@example.com","password":"password494"},{"email":"example495@example.com","password":"password495"},{"email":"example496@example.com","password":"password496"},{"email":"example497@example.com","password":"password497"},{"email":"example498@example.com","password":"password498"},{"email":"example499@example.com","password":"password499"},{"email":"example500@example.com","password":"password500"}]